7-Segment Display Decoder/design.sv
module seven_segment_decoder(
    input [3:0] digit,
    output reg [6:0] segment
);

    always @(digit) begin
        case (digit)
            4'h0: segment = 7'b1000000; // 0
            4'h1: segment = 7'b1111001; // 1
            4'h2: segment = 7'b0100100; // 2
            4'h3: segment = 7'b0110000; // 3
            4'h4: segment = 7'b0011001; // 4
            4'h5: segment = 7'b0010010; // 5
            4'h6: segment = 7'b0000010; // 6
            4'h7: segment = 7'b1111000; // 7
            4'h8: segment = 7'b0000000; // 8
            4'h9: segment = 7'b0010000; // 9
            default: segment = 7'b1111111; // Blank
        endcase
    end

endmodule

7-Segment Display Decoder/testbench.sv
`timescale 1ns / 1ps

module seven_segment_decoder_tb;

    // Inputs
    reg [3:0] digit;

    // Outputs
    wire [6:0] segment;

    // Instantiate the Unit Under Test (UUT)
    seven_segment_decoder uut (
        .digit(digit), 
        .segment(segment)
    );

    initial begin
        // Initialize Inputs
        digit = 0;

        // Initialize VCD output
        $dumpfile("seven_segment_decoder.vcd");
        $dumpvars(0, seven_segment_decoder_tb);

        // Wait 100 ns for global reset to finish
        #20;

        // Add stimulus here
        digit = 4'b0000; #10;
        digit = 4'b0001; #10;
        digit = 4'b0010; #10;
        digit = 4'b0011; #10;
        digit = 4'b0100; #10;
        digit = 4'b0101; #10;
        digit = 4'b0110; #10;
        digit = 4'b0111; #10;
        digit = 4'b1000; #10;
        digit = 4'b1001; #10;

        // Finish simulation
        $finish;
    end

endmodule

7-Segment Display Decoder/seven_segment_decoder.vcd
$date
	Mon Apr 22 02:31:39 2024
$end
$version
	Icarus Verilog
$end
$timescale
	1ps
$end
$scope module seven_segment_decoder_tb $end
$var wire 7 ! segment [6:0] $end
$var reg 4 " digit [3:0] $end
$scope module uut $end
$var wire 4 # digit [3:0] $end
$var reg 7 $ segment [6:0] $end
$upscope $end
$upscope $end
$enddefinitions $end
#0
$dumpvars
b1000000 $
b0 #
b0 "
b1000000 !
$end
#30000
b1111001 $
b1111001 !
b1 "
b1 #
#40000
b100100 $
b100100 !
b10 "
b10 #
#50000
b110000 $
b110000 !
b11 "
b11 #
#60000
b11001 $
b11001 !
b100 "
b100 #
#70000
b10010 $
b10010 !
b101 "
b101 #
#80000
b10 $
b10 !
b110 "
b110 #
#90000
b1111000 $
b1111000 !
b111 "
b111 #
#100000
b0 $
b0 !
b1000 "
b1000 #
#110000
b10000 $
b10000 !
b1001 "
b1001 #
