Accumulator with TB (Output Fixed)/design.sv
module accumulator(
    input wire clk,
    input wire rst,
    input wire add_sub, // 0 for addition, 1 for subtraction
    input wire [7:0] data_in,
    output reg [15:0] acc
);

always @(posedge clk or posedge rst)
begin
    if (rst)
        acc <= 0;
    else if (add_sub)
        acc <= acc - data_in;
    else
        acc <= acc + data_in;
end

endmodule

Accumulator with TB (Output Fixed)/testbench.sv
`timescale 1ns / 1ps

module accumulator_tb;

// Parameters
parameter PERIOD = 10; // Simulation period

// Signals
reg clk = 0, rst = 1, add_sub = 0;
reg [7:0] data_in = 8'h00;
wire [15:0] acc;

// Instantiate the accumulator
accumulator Acc (
    .clk(clk),
    .rst(rst),
    .add_sub(add_sub),
    .data_in(data_in),
    .acc(acc)
);

// Clock generation
always #5 clk = ~clk;

// Stimulus
initial begin
    $dumpfile("accumulator_tb.vcd");
    $dumpvars(0, accumulator_tb);

    // Reset
    #PERIOD;
    rst = 0;
    #PERIOD;

    // Add some values
    data_in = 8'h05; // Add 5
    add_sub = 0;
    #PERIOD;
    
    data_in = 8'h0A; // Add 10
    #PERIOD;
    
    // Subtract some values
    data_in = 8'h03; // Subtract 3
    add_sub = 1;
    #PERIOD;
    
    data_in = 8'h04; // Subtract 4
    #PERIOD;
    
    $finish;
end

endmodule

Accumulator with TB (Output Fixed)/accumulator_tb.vcd
$date
	Sun Apr 14 16:44:29 2024
$end
$version
	Icarus Verilog
$end
$timescale
	1ps
$end
$scope module accumulator_tb $end
$var wire 16 ! acc [15:0] $end
$var reg 1 " add_sub $end
$var reg 1 # clk $end
$var reg 8 $ data_in [7:0] $end
$var reg 1 % rst $end
$scope module Acc $end
$var wire 1 & add_sub $end
$var wire 1 ' clk $end
$var wire 8 ( data_in [7:0] $end
$var wire 1 ) rst $end
$var reg 16 * acc [15:0] $end
$upscope $end
$upscope $end
$enddefinitions $end
#0
$dumpvars
b0 *
1)
b0 (
0'
0&
1%
b0 $
0#
0"
b0 !
$end
#5000
1#
1'
#10000
0#
0'
0%
0)
#15000
1#
1'
#20000
0#
0'
b101 $
b101 (
#25000
b101 *
b101 !
1#
1'
#30000
0#
0'
b1010 $
b1010 (
#35000
b1111 *
b1111 !
1#
1'
#40000
0#
0'
1"
1&
b11 $
b11 (
#45000
b1100 *
b1100 !
1#
1'
#50000
0#
0'
b100 $
b100 (
#55000
b1000 *
b1000 !
1#
1'
