FIFO with TB/testbench.sv
// FIFO module
module fifo(
    input wire clk,
    input wire rst,
    input wire wr_en,
    input wire rd_en,
    input wire [7:0] data_in,
    output reg [7:0] data_out,
    output reg empty,
    output reg full
);

parameter DEPTH = 8; // Depth of the FIFO

reg [7:0] memory [0:DEPTH-1];
reg [3:0] wr_ptr = 4'b0000; // Write pointer
reg [3:0] rd_ptr = 4'b0000; // Read pointer

always @(posedge clk or posedge rst) begin
    if (rst) begin
        wr_ptr <= 4'b0000;
        rd_ptr <= 4'b0000;
        empty <= 1'b1;
        full <= 1'b0;
        data_out <= 8'b0;
    end else begin
        // Write operation
        if (wr_en && !full) begin
            memory[wr_ptr] <= data_in;
            wr_ptr <= wr_ptr + 1;
            if (wr_ptr == DEPTH) wr_ptr <= 0;
            empty <= 0;
            if (wr_ptr == rd_ptr) full <= 1;
        end
        // Read operation
        if (rd_en && !empty) begin
            data_out <= memory[rd_ptr];
            rd_ptr <= rd_ptr + 1;
            if (rd_ptr == DEPTH) rd_ptr <= 0;
            full <= 0;
            if (rd_ptr == wr_ptr) empty <= 1;
        end
    end
end

endmodule

FIFO with TB/design.sv
// Testbench for FIFO module with multiple test cases and VCD output
module fifo_tb;

parameter CLK_PERIOD = 10; // Clock period in ns
parameter TEST_CASES = 10; // Number of test cases

reg clk;
reg rst;
reg wr_en;
reg rd_en;
reg [7:0] data_in;
wire [7:0] data_out;
wire empty;
wire full;

fifo dut (
    .clk(clk),
    .rst(rst),
    .wr_en(wr_en),
    .rd_en(rd_en),
    .data_in(data_in),
    .data_out(data_out),
    .empty(empty),
    .full(full)
);

initial begin
    $dumpfile("fifo_tb.vcd"); // Specify the VCD file name
    $dumpvars(0, fifo_tb); // Dump all variables to VCD file
    clk = 0;
    forever #((CLK_PERIOD)/2) clk = ~clk;
end

initial begin
    rst = 1;
    wr_en = 0;
    rd_en = 0;
    data_in = 8'b0;
    #100 rst = 0;
    #10;

    // Test cases
    repeat (TEST_CASES) begin
        wr_en = 1;
        data_in = $random; // Generate random data
        #20;
        wr_en = 0;
        rd_en = 1;
        #20;
        rd_en = 0;
    end

    $finish;
end

endmodule

FIFO with TB/fifo_tb.vcd
$date
	Sat Apr 20 17:26:40 2024
$end
$version
	Icarus Verilog
$end
$timescale
	1s
$end
$scope module fifo_tb $end
$var wire 8 ! data_out [7:0] $end
$var wire 1 " empty $end
$var wire 1 # full $end
$var reg 1 $ clk $end
$var reg 8 % data_in [7:0] $end
$var reg 1 & rd_en $end
$var reg 1 ' rst $end
$var reg 1 ( wr_en $end
$scope module dut $end
$var wire 1 ) clk $end
$var wire 8 * data_in [7:0] $end
$var wire 1 + rd_en $end
$var wire 1 , rst $end
$var wire 1 - wr_en $end
$var reg 8 . data_out [7:0] $end
$var reg 1 / empty $end
$var reg 1 0 full $end
$var reg 4 1 rd_ptr [3:0] $end
$var reg 4 2 wr_ptr [3:0] $end
$upscope $end
$upscope $end
$enddefinitions $end
#0
$dumpvars
b0 2
b0 1
00
1/
b0 .
0-
1,
0+
b0 *
0)
0(
1'
0&
b0 %
0$
0#
1"
b0 !
$end
#5
1$
1)
#10
0$
0)
#15
1$
1)
#20
0$
0)
#25
1$
1)
#30
0$
0)
#35
1$
1)
#40
0$
0)
#45
1$
1)
#50
0$
0)
#55
1$
1)
#60
0$
0)
#65
1$
1)
#70
0$
0)
#75
1$
1)
#80
0$
0)
#85
1$
1)
#90
0$
0)
#95
1$
1)
#100
0$
0)
0'
0,
#105
1$
1)
#110
0$
0)
b100100 %
b100100 *
1(
1-
#115
10
1#
0/
0"
b1 2
1$
1)
#120
0$
0)
#125
1$
1)
#130
0$
0)
1&
1+
0(
0-
#135
00
0#
b1 1
b100100 .
b100100 !
1$
1)
#140
0$
0)
#145
1/
1"
b10 1
bx .
bx !
1$
1)
#150
0$
0)
b10000001 %
b10000001 *
1(
1-
0&
0+
#155
0/
0"
b10 2
1$
1)
#160
0$
0)
#165
10
1#
b11 2
1$
1)
#170
0$
0)
1&
1+
0(
0-
#175
00
0#
b11 1
b10000001 .
b10000001 !
1$
1)
#180
0$
0)
#185
1/
1"
b100 1
bx .
bx !
1$
1)
#190
0$
0)
b1001 %
b1001 *
1(
1-
0&
0+
#195
0/
0"
b100 2
1$
1)
#200
0$
0)
#205
10
1#
b101 2
1$
1)
#210
0$
0)
1&
1+
0(
0-
#215
00
0#
b101 1
b1001 .
b1001 !
1$
1)
#220
0$
0)
#225
1/
1"
b110 1
bx .
bx !
1$
1)
#230
0$
0)
b1100011 %
b1100011 *
1(
1-
0&
0+
#235
0/
0"
b110 2
1$
1)
#240
0$
0)
#245
10
1#
b111 2
1$
1)
#250
0$
0)
1&
1+
0(
0-
#255
00
0#
b111 1
b1100011 .
b1100011 !
1$
1)
#260
0$
0)
#265
1/
1"
b1000 1
bx .
bx !
1$
1)
#270
0$
0)
b1101 %
b1101 *
1(
1-
0&
0+
#275
0/
0"
b1000 2
1$
1)
#280
0$
0)
#285
10
1#
b0 2
1$
1)
#290
0$
0)
1&
1+
0(
0-
#295
00
0#
b0 1
1$
1)
#300
0$
0)
#305
1/
1"
b1 1
b100100 .
b100100 !
1$
1)
#310
0$
0)
b10001101 %
b10001101 *
1(
1-
0&
0+
#315
0/
0"
b1 2
1$
1)
#320
0$
0)
#325
10
1#
b10 2
1$
1)
#330
0$
0)
1&
1+
0(
0-
#335
00
0#
b10 1
b10001101 .
b10001101 !
1$
1)
#340
0$
0)
#345
1/
1"
b11 1
b10000001 .
b10000001 !
1$
1)
#350
0$
0)
b1100101 %
b1100101 *
1(
1-
0&
0+
#355
0/
0"
b11 2
1$
1)
#360
0$
0)
#365
10
1#
b100 2
1$
1)
#370
0$
0)
1&
1+
0(
0-
#375
00
0#
b100 1
b1100101 .
b1100101 !
1$
1)
#380
0$
0)
#385
1/
1"
b101 1
b1001 .
b1001 !
1$
1)
#390
0$
0)
b10010 %
b10010 *
1(
1-
0&
0+
#395
0/
0"
b101 2
1$
1)
#400
0$
0)
#405
10
1#
b110 2
1$
1)
#410
0$
0)
1&
1+
0(
0-
#415
00
0#
b110 1
b10010 .
b10010 !
1$
1)
#420
0$
0)
#425
1/
1"
b111 1
b1100011 .
b1100011 !
1$
1)
#430
0$
0)
b1 %
b1 *
1(
1-
0&
0+
#435
0/
0"
b111 2
1$
1)
#440
0$
0)
#445
10
1#
b1000 2
1$
1)
#450
0$
0)
1&
1+
0(
0-
#455
00
0#
b1000 1
b1 .
b1 !
1$
1)
#460
0$
0)
#465
1/
1"
b0 1
bx .
bx !
1$
1)
#470
0$
0)
b1101 %
b1101 *
1(
1-
0&
0+
#475
0/
0"
b0 2
1$
1)
#480
0$
0)
#485
10
1#
b1 2
1$
1)
#490
0$
0)
1&
1+
0(
0-
#495
00
0#
b1 1
b1101 .
b1101 !
1$
1)
#500
0$
0)
#505
1/
1"
b10 1
b10001101 .
b10001101 !
1$
1)
#510
0$
0)
0&
0+
