Signed Multiplier_Divider with TB/design.sv
module signed_mult_div(
    input signed [7:0] a,
    input signed [7:0] b,
    output reg signed [15:0] mult,
    output reg signed [7:0] div,
    output reg div_by_zero // This flag is high if division by zero is attempted
);

always @(*) begin
    // Perform signed multiplication
    mult = a * b;

    // Perform signed division
    if (b != 0) begin
        div = a / b;
        div_by_zero = 1'b0;
    end else begin
        div = 0; // Assign a default value when division by zero is attempted
        div_by_zero = 1'b1;
    end
end

endmodule

Signed Multiplier_Divider with TB/testbench.sv
`timescale 1ns / 1ps

module signed_mult_div_tb;

reg signed [7:0] a, b;
wire signed [15:0] mult;
wire signed [7:0] div;
wire div_by_zero;

signed_mult_div uut(
    .a(a),
    .b(b),
    .mult(mult),
    .div(div),
    .div_by_zero(div_by_zero)
);

initial begin
    // Initialize inputs
    a = 0;
    b = 0;

    // Create VCD file
    $dumpfile("signed_mult_div.vcd");
    $dumpvars(0, signed_mult_div_tb);

    // Test cases
    #10 a = 8'd127; b = 8'd127; // Case 1: Max positive numbers
    #10 a = -8'd128; b = 8'd127; // Case 2: Max negative and max positive
    #10 a = 8'd127; b = -8'd128; // Case 3: Max positive and max negative
    #10 a = -8'd128; b = -8'd128; // Case 4: Max negative numbers
    #10 a = 8'd10; b = 8'd5; // Case 5: Positive division
    #10 a = -8'd10; b = 8'd5; // Case 6: Negative division (numerator)
    #10 a = 8'd10; b = -8'd5; // Case 7: Negative division (denominator)
    #10 a = -8'd10; b = -8'd5; // Case 8: Negative division (both)
    #10 a = 8'd10; b = 8'd0; // Case 9: Division by zero
    #10 a = 0; b = -8'd10; // Case 10: Zero numerator

    #10 $finish; // End simulation
end

endmodule

Signed Multiplier_Divider with TB/signed_mult_div.vcd
$date
	Mon Apr 22 02:49:17 2024
$end
$version
	Icarus Verilog
$end
$timescale
	1ps
$end
$scope module signed_mult_div_tb $end
$var wire 8 ! div [7:0] $end
$var wire 1 " div_by_zero $end
$var wire 16 # mult [15:0] $end
$var reg 8 $ a [7:0] $end
$var reg 8 % b [7:0] $end
$scope module uut $end
$var wire 8 & a [7:0] $end
$var wire 8 ' b [7:0] $end
$var reg 8 ( div [7:0] $end
$var reg 1 ) div_by_zero $end
$var reg 16 * mult [15:0] $end
$upscope $end
$upscope $end
$enddefinitions $end
#0
$dumpvars
b0 *
1)
b0 (
b0 '
b0 &
b0 %
b0 $
b0 #
1"
b0 !
$end
#10000
0)
0"
b1 (
b1 !
b11111100000001 *
b11111100000001 #
b1111111 %
b1111111 '
b1111111 $
b1111111 &
#20000
b11111111 (
b11111111 !
b1100000010000000 *
b1100000010000000 #
b10000000 $
b10000000 &
#30000
b0 (
b0 !
b10000000 %
b10000000 '
b1111111 $
b1111111 &
#40000
b1 (
b1 !
b100000000000000 *
b100000000000000 #
b10000000 $
b10000000 &
#50000
b10 (
b10 !
b110010 *
b110010 #
b101 %
b101 '
b1010 $
b1010 &
#60000
b11111110 (
b11111110 !
b1111111111001110 *
b1111111111001110 #
b11110110 $
b11110110 &
#70000
b11111011 %
b11111011 '
b1010 $
b1010 &
#80000
b10 (
b10 !
b110010 *
b110010 #
b11110110 $
b11110110 &
#90000
1)
1"
b0 (
b0 !
b0 *
b0 #
b0 %
b0 '
b1010 $
b1010 &
#100000
0)
0"
b11110110 %
b11110110 '
b0 $
b0 &
