8-Bit Memory with TB/design.sv
// 8-bit memory module
module memory_module (
    input wire clk,
    input wire we,                 // Write enable
    input wire [7:0] addr,         // Address bus
    input wire [7:0] data_in,      // Data input bus
    output reg [7:0] data_out      // Data output bus
);

    // Define the memory size
    parameter MEM_DEPTH = 256;
    
    // Memory array
    reg [7:0] mem [0:MEM_DEPTH-1];

    // Write operation
    always @(posedge clk) begin
        if (we) begin
            mem[addr] <= data_in;
        end
    end
    
    // Read operation
    always @(posedge clk) begin
        if (!we) begin
            data_out <= mem[addr];
        end
    end

endmodule

8-Bit Memory with TB/testbench.sv
// Testbench
module testbench;
    reg clk;
    reg we;
    reg [7:0] addr;
    reg [7:0] data_in;
    wire [7:0] data_out;

    // Instantiate the memory module
    memory_module uut (
        .clk(clk),
        .we(we),
        .addr(addr),
        .data_in(data_in),
        .data_out(data_out)
    );

    // Clock generation
    initial begin
        clk = 0;
        forever #2 clk = ~clk; // Generate a clock with a period of 4 time units
    end

    // Test cases
    initial begin
        // Initialize signals
        we = 0;
        addr = 0;
        data_in = 0;
        
        // Initialize VCD dump
        $dumpfile("memory.vcd");
        $dumpvars(0, testbench);
        
        // Test case 1: Write to memory location 0
        #10 we = 1; addr = 8'h00; data_in = 8'hAA;
        #10 we = 0;

        // Test case 2: Write to memory location 1
        #10 we = 1; addr = 8'h01; data_in = 8'hBB;
        #10 we = 0;

        // Test case 3: Write to memory location 2
        #10 we = 1; addr = 8'h02; data_in = 8'hCC;
        #10 we = 0;

        // Test case 4: Write to memory location 3
        #10 we = 1; addr = 8'h03; data_in = 8'hDD;
        #10 we = 0;

        // Test case 5: Write to memory location 3
        #10 we = 1; addr = 8'h04; data_in = 8'hEE;
        #10 we = 0;      
      
        // Test case 6: Write to memory location 3
        #10 we = 1; addr = 8'h05; data_in = 8'hFF;
        #10 we = 0;    
      
        // Test case 7: Write to memory location 3
        #10 we = 1; addr = 8'h06; data_in = 8'hA0;
        #10 we = 0;
      
        // Test case 8: Write to memory location 3
        #10 we = 1; addr = 8'h07; data_in = 8'hB0;
        #10 we = 0;
      
        // Test case 9: Write to memory location 3
        #10 we = 1; addr = 8'h08; data_in = 8'hC0;
        #10 we = 0;
      
            
        // Test case 10: Read from the previously written memory locations
        #10 addr = 8'h00; // Read from location 0
        #10 addr = 8'h01; // Read from location 1
        #10 addr = 8'h02; // Read from location 2
        #10 addr = 8'h03; // Read from location 3
        #10 addr = 8'h04; // Read from location 4
        #10 addr = 8'h05; // Read from location 5
        #10 addr = 8'h06; // Read from location 6
        #10 addr = 8'h07; // Read from location 7      
        #10 addr = 8'h08; // Read from location 8
        #10 addr = 8'h09; // Read from location 9
        #10 addr = 8'h0A; // Read from location a
        #10 addr = 8'h0B; // Read from location b 
        #10 addr = 8'h0C; // Read from location c
        #10 addr = 8'h0D; // Read from location d
             

        #10;

        // Finish the simulation
        $finish;
    end
endmodule

8-Bit Memory with TB/memory.vcd
$date
	Sun Apr 21 20:40:01 2024
$end
$version
	Icarus Verilog
$end
$timescale
	1s
$end
$scope module testbench $end
$var wire 8 ! data_out [7:0] $end
$var reg 8 " addr [7:0] $end
$var reg 1 # clk $end
$var reg 8 $ data_in [7:0] $end
$var reg 1 % we $end
$scope module uut $end
$var wire 8 & addr [7:0] $end
$var wire 1 ' clk $end
$var wire 8 ( data_in [7:0] $end
$var wire 1 ) we $end
$var reg 8 * data_out [7:0] $end
$upscope $end
$upscope $end
$enddefinitions $end
#0
$dumpvars
bx *
0)
b0 (
0'
b0 &
0%
b0 $
0#
b0 "
bx !
$end
#2
1#
1'
#4
0#
0'
#6
1#
1'
#8
0#
0'
#10
1#
1'
b10101010 $
b10101010 (
1%
1)
#12
0#
0'
#14
1#
1'
#16
0#
0'
#18
1#
1'
#20
0#
0'
0%
0)
#22
b10101010 *
b10101010 !
1#
1'
#24
0#
0'
#26
1#
1'
#28
0#
0'
#30
1#
1'
b10111011 $
b10111011 (
b1 "
b1 &
1%
1)
#32
0#
0'
#34
1#
1'
#36
0#
0'
#38
1#
1'
#40
0#
0'
0%
0)
#42
b10111011 *
b10111011 !
1#
1'
#44
0#
0'
#46
1#
1'
#48
0#
0'
#50
1#
1'
b11001100 $
b11001100 (
b10 "
b10 &
1%
1)
#52
0#
0'
#54
1#
1'
#56
0#
0'
#58
1#
1'
#60
0#
0'
0%
0)
#62
b11001100 *
b11001100 !
1#
1'
#64
0#
0'
#66
1#
1'
#68
0#
0'
#70
1#
1'
b11011101 $
b11011101 (
b11 "
b11 &
1%
1)
#72
0#
0'
#74
1#
1'
#76
0#
0'
#78
1#
1'
#80
0#
0'
0%
0)
#82
b11011101 *
b11011101 !
1#
1'
#84
0#
0'
#86
1#
1'
#88
0#
0'
#90
1#
1'
b11101110 $
b11101110 (
b100 "
b100 &
1%
1)
#92
0#
0'
#94
1#
1'
#96
0#
0'
#98
1#
1'
#100
0#
0'
0%
0)
#102
b11101110 *
b11101110 !
1#
1'
#104
0#
0'
#106
1#
1'
#108
0#
0'
#110
1#
1'
b11111111 $
b11111111 (
b101 "
b101 &
1%
1)
#112
0#
0'
#114
1#
1'
#116
0#
0'
#118
1#
1'
#120
0#
0'
0%
0)
#122
b11111111 *
b11111111 !
1#
1'
#124
0#
0'
#126
1#
1'
#128
0#
0'
#130
1#
1'
b10100000 $
b10100000 (
b110 "
b110 &
1%
1)
#132
0#
0'
#134
1#
1'
#136
0#
0'
#138
1#
1'
#140
0#
0'
0%
0)
#142
b10100000 *
b10100000 !
1#
1'
#144
0#
0'
#146
1#
1'
#148
0#
0'
#150
1#
1'
b10110000 $
b10110000 (
b111 "
b111 &
1%
1)
#152
0#
0'
#154
1#
1'
#156
0#
0'
#158
1#
1'
#160
0#
0'
0%
0)
#162
b10110000 *
b10110000 !
1#
1'
#164
0#
0'
#166
1#
1'
#168
0#
0'
#170
1#
1'
b11000000 $
b11000000 (
b1000 "
b1000 &
1%
1)
#172
0#
0'
#174
1#
1'
#176
0#
0'
#178
1#
1'
#180
0#
0'
0%
0)
#182
b11000000 *
b11000000 !
1#
1'
#184
0#
0'
#186
1#
1'
#188
0#
0'
#190
b10101010 *
b10101010 !
1#
1'
b0 "
b0 &
#192
0#
0'
#194
1#
1'
#196
0#
0'
#198
1#
1'
#200
0#
0'
b1 "
b1 &
#202
b10111011 *
b10111011 !
1#
1'
#204
0#
0'
#206
1#
1'
#208
0#
0'
#210
b11001100 *
b11001100 !
1#
1'
b10 "
b10 &
#212
0#
0'
#214
1#
1'
#216
0#
0'
#218
1#
1'
#220
0#
0'
b11 "
b11 &
#222
b11011101 *
b11011101 !
1#
1'
#224
0#
0'
#226
1#
1'
#228
0#
0'
#230
b11101110 *
b11101110 !
1#
1'
b100 "
b100 &
#232
0#
0'
#234
1#
1'
#236
0#
0'
#238
1#
1'
#240
0#
0'
b101 "
b101 &
#242
b11111111 *
b11111111 !
1#
1'
#244
0#
0'
#246
1#
1'
#248
0#
0'
#250
b10100000 *
b10100000 !
1#
1'
b110 "
b110 &
#252
0#
0'
#254
1#
1'
#256
0#
0'
#258
1#
1'
#260
0#
0'
b111 "
b111 &
#262
b10110000 *
b10110000 !
1#
1'
#264
0#
0'
#266
1#
1'
#268
0#
0'
#270
b11000000 *
b11000000 !
1#
1'
b1000 "
b1000 &
#272
0#
0'
#274
1#
1'
#276
0#
0'
#278
1#
1'
#280
0#
0'
b1001 "
b1001 &
#282
bx *
bx !
1#
1'
#284
0#
0'
#286
1#
1'
#288
0#
0'
#290
1#
1'
b1010 "
b1010 &
#292
0#
0'
#294
1#
1'
#296
0#
0'
#298
1#
1'
#300
0#
0'
b1011 "
b1011 &
#302
1#
1'
#304
0#
0'
#306
1#
1'
#308
0#
0'
#310
1#
1'
b1100 "
b1100 &
#312
0#
0'
#314
1#
1'
#316
0#
0'
#318
1#
1'
#320
0#
0'
b1101 "
b1101 &
