UART TX + RX with TB/design.sv
`timescale 1ns / 1ps

module uart_tx (
    input wire clk,
    input wire reset,
    input wire [7:0] data_in,
    input wire transmit,
    output reg tx,
    output reg tx_done
);

parameter IDLE = 0;
parameter SEND = 1;

reg [3:0] bit_index;
reg [1:0] state;

always @(posedge clk or posedge reset) begin
    if (reset) begin
        state <= IDLE;
        tx <= 1'b1; // Idle state for UART is high
        tx_done <= 1'b0;
        bit_index <= 0;
    end else begin
        case (state)
            IDLE: begin
                tx_done <= 1'b0;
                if (transmit) begin
                    tx <= 0; // Start bit
                    bit_index <= 0;
                    state <= SEND;
                end
            end
            SEND: begin
                tx <= data_in[bit_index];
                bit_index <= bit_index + 1;
                if (bit_index == 8) begin
                    state <= IDLE;
                    tx_done <= 1'b1;
                end
            end
        endcase
    end
end

endmodule



///////////////////////////////////////////////////


module uart_rx (
    input wire clk,
    input wire reset,
    input wire rx,
    output reg [7:0] data_out,
    output reg rx_done
);

parameter IDLE = 0;
parameter RECEIVE = 1;

reg [3:0] bit_index;
reg [1:0] state;

always @(posedge clk or posedge reset) begin
    if (reset) begin
        state <= IDLE;
        rx_done <= 1'b0;
        bit_index <= 0;
    end else begin
        case (state)
            IDLE: begin
                rx_done <= 1'b0;
                if (rx == 0) begin // Start bit detected
                    bit_index <= 0;
                    state <= RECEIVE;
                end
            end
            RECEIVE: begin
                data_out[bit_index] <= rx;
                bit_index <= bit_index + 1;
                if (bit_index == 8) begin
                    state <= IDLE;
                    rx_done <= 1'b1;
                end
            end
        endcase
    end
end

endmodule

UART TX + RX with TB/testbench.sv
`timescale 1ns / 1ps

module uart_tb();

    reg clk;
    reg reset;
    reg [7:0] test_data [9:0];
    reg transmit;
    wire tx;
    wire tx_done;
    wire [7:0] rx_data;
    wire rx_done;
    integer i;

    // Instantiate the UART transmitter and receiver
    uart_tx tx_unit(
        .clk(clk),
        .reset(reset),
        .data_in(test_data[i]),
        .transmit(transmit),
        .tx(tx),
        .tx_done(tx_done)
    );

    uart_rx rx_unit(
        .clk(clk),
        .reset(reset),
        .rx(tx), // Directly connect tx to rx for loopback test
        .data_out(rx_data),
        .rx_done(rx_done)
    );

    // Clock generation
    always #5 clk = ~clk;

    initial begin
        // Initialize test data
        test_data[0] = 8'hA1;
        test_data[1] = 8'hB2;
        test_data[2] = 8'hC3;
        test_data[3] = 8'hD4;
        test_data[4] = 8'hE5;
        test_data[5] = 8'hF6;
        test_data[6] = 8'h07;
        test_data[7] = 8'h18;
        test_data[8] = 8'h29;
        test_data[9] = 8'h3A;

        // Initialize signals
        clk = 0;
        reset = 1;
        transmit = 0;

        // VCD file generation for waveform analysis
        $dumpfile("uart_test.vcd");
        $dumpvars(0, uart_tb);

        // Reset the system
        #20 reset = 0;
        #20;

        // Start the test cases
        for (i = 0; i < 10; i = i + 1) begin
            #20 transmit = 1; // Start transmission
            #20 transmit = 0; // Stop transmission request
            
            // Wait for transmission to complete
            wait(tx_done);
            #20; // Give some time for the receiver to process the last bit

            // Wait for reception to complete
            wait(rx_done);
            
            // Check the received data
            if (rx_data !== test_data[i]) begin
                $display("Test case %d failed: Sent %h, Received %h", i, test_data[i], rx_data);
            end else begin
                $display("Test case %d passed: Sent %h, Received %h", i, test_data[i], rx_data);
            end
            
            #100; // Wait a while before the next test case
        end

        $display("Testing completed");
        $finish;
    end

endmodule

UART TX + RX with TB/uart_test.vcd
$date
	Sun Apr 21 22:17:05 2024
$end
$version
	Icarus Verilog
$end
$timescale
	1ps
$end
$scope module uart_tb $end
$var wire 8 ! rx_data [7:0] $end
$var wire 1 " rx_done $end
$var wire 1 # tx $end
$var wire 1 $ tx_done $end
$var reg 1 % clk $end
$var integer 32 & i [31:0] $end
$var reg 1 ' reset $end
$var reg 1 ( transmit $end
$scope module tx_unit $end
$var wire 1 ) clk $end
$var wire 8 * data_in [7:0] $end
$var wire 1 + reset $end
$var wire 1 , transmit $end
$var reg 4 - bit_index [3:0] $end
$var reg 2 . state [1:0] $end
$var reg 1 / tx $end
$var reg 1 0 tx_done $end
$upscope $end
$scope module rx_unit $end
$var wire 1 ) clk $end
$var wire 1 + reset $end
$var wire 1 # rx $end
$var reg 4 1 bit_index [3:0] $end
$var reg 8 2 data_out [7:0] $end
$var reg 1 3 rx_done $end
$var reg 2 4 state [1:0] $end
$upscope $end
$upscope $end
$enddefinitions $end
#0
$dumpvars
b0 4
03
bx 2
b0 1
00
1/
b0 .
b0 -
0,
1+
bx *
0)
0(
1'
bx &
0%
0$
1#
0"
bx !
$end
#5000
1%
1)
#10000
0%
0)
#15000
1%
1)
#20000
0%
0)
0'
0+
#25000
1%
1)
#30000
0%
0)
#35000
1%
1)
#40000
0%
0)
b0 &
b10100001 *
#45000
1%
1)
#50000
0%
0)
#55000
1%
1)
#60000
0%
0)
1(
1,
#65000
b1 .
0/
0#
1%
1)
#70000
0%
0)
#75000
b1 -
1/
1#
b1 4
1%
1)
#80000
0%
0)
0(
0,
#85000
b1 1
bx1 2
bx1 !
b10 -
0/
0#
1%
1)
#90000
0%
0)
#95000
b11 -
b10 1
bx01 2
bx01 !
1%
1)
#100000
0%
0)
#105000
b11 1
bx001 2
bx001 !
b100 -
1%
1)
#110000
0%
0)
#115000
b101 -
b100 1
bx0001 2
bx0001 !
1%
1)
#120000
0%
0)
#125000
b101 1
bx00001 2
bx00001 !
b110 -
1/
1#
1%
1)
#130000
0%
0)
#135000
b111 -
0/
0#
b110 1
bx100001 2
bx100001 !
1%
1)
#140000
0%
0)
#145000
b111 1
bx0100001 2
bx0100001 !
b1000 -
1/
1#
1%
1)
#150000
0%
0)
#155000
10
1$
b0 .
b1001 -
x/
x#
b1000 1
b10100001 2
b10100001 !
1%
1)
#160000
0%
0)
#165000
13
1"
b0 4
b1001 1
00
0$
1%
1)
#170000
0%
0)
#175000
03
0"
1%
1)
#180000
0%
0)
#185000
1%
1)
#190000
0%
0)
#195000
1%
1)
#200000
0%
0)
#205000
1%
1)
#210000
0%
0)
#215000
1%
1)
#220000
0%
0)
#225000
1%
1)
#230000
0%
0)
#235000
1%
1)
#240000
0%
0)
#245000
1%
1)
#250000
0%
0)
#255000
1%
1)
#260000
0%
0)
#265000
1%
1)
#270000
0%
0)
#275000
1%
1)
b1 &
b10110010 *
#280000
0%
0)
#285000
1%
1)
#290000
0%
0)
#295000
b1 .
b0 -
0/
0#
1%
1)
1(
1,
#300000
0%
0)
#305000
b1 4
b0 1
b1 -
1%
1)
#310000
0%
0)
#315000
b10 -
1/
1#
b1 1
b10100000 2
b10100000 !
1%
1)
0(
0,
#320000
0%
0)
#325000
b10 1
b10100010 2
b10100010 !
b11 -
0/
0#
1%
1)
#330000
0%
0)
#335000
b100 -
b11 1
b10100010 2
1%
1)
#340000
0%
0)
#345000
b100 1
b10100010 2
b101 -
1/
1#
1%
1)
#350000
0%
0)
#355000
b110 -
b101 1
b10110010 2
b10110010 !
1%
1)
#360000
0%
0)
#365000
b110 1
b10110010 2
b111 -
0/
0#
1%
1)
#370000
0%
0)
#375000
b1000 -
1/
1#
b111 1
b10110010 2
1%
1)
#380000
0%
0)
#385000
b1000 1
b10110010 2
10
1$
b0 .
b1001 -
x/
x#
1%
1)
#390000
0%
0)
#395000
00
0$
13
1"
b0 4
b1001 1
1%
1)
#400000
0%
0)
#405000
03
0"
1%
1)
#410000
0%
0)
#415000
1%
1)
#420000
0%
0)
#425000
1%
1)
#430000
0%
0)
#435000
1%
1)
#440000
0%
0)
#445000
1%
1)
#450000
0%
0)
#455000
1%
1)
#460000
0%
0)
#465000
1%
1)
#470000
0%
0)
#475000
1%
1)
#480000
0%
0)
#485000
1%
1)
#490000
0%
0)
#495000
1%
1)
#500000
0%
0)
#505000
1%
1)
b10 &
b11000011 *
#510000
0%
0)
#515000
1%
1)
#520000
0%
0)
#525000
b1 .
b0 -
0/
0#
1%
1)
1(
1,
#530000
0%
0)
#535000
b1 -
1/
1#
b1 4
b0 1
1%
1)
#540000
0%
0)
#545000
b1 1
b10110011 2
b10110011 !
b10 -
1%
1)
0(
0,
#550000
0%
0)
#555000
b11 -
0/
0#
b10 1
b10110011 2
1%
1)
#560000
0%
0)
#565000
b11 1
b10110011 2
b100 -
1%
1)
#570000
0%
0)
#575000
b101 -
b100 1
b10110011 2
1%
1)
#580000
0%
0)
#585000
b101 1
b10100011 2
b10100011 !
b110 -
1%
1)
#590000
0%
0)
#595000
b111 -
1/
1#
b110 1
b10000011 2
b10000011 !
1%
1)
#600000
0%
0)
#605000
b111 1
b11000011 2
b11000011 !
b1000 -
1%
1)
#610000
0%
0)
#615000
10
1$
b0 .
b1001 -
x/
x#
b1000 1
b11000011 2
1%
1)
#620000
0%
0)
#625000
13
1"
b0 4
b1001 1
00
0$
1%
1)
#630000
0%
0)
#635000
03
0"
1%
1)
#640000
0%
0)
#645000
1%
1)
#650000
0%
0)
#655000
1%
1)
#660000
0%
0)
#665000
1%
1)
#670000
0%
0)
#675000
1%
1)
#680000
0%
0)
#685000
1%
1)
#690000
0%
0)
#695000
1%
1)
#700000
0%
0)
#705000
1%
1)
#710000
0%
0)
#715000
1%
1)
#720000
0%
0)
#725000
1%
1)
#730000
0%
0)
#735000
1%
1)
b11 &
b11010100 *
#740000
0%
0)
#745000
1%
1)
#750000
0%
0)
#755000
b1 .
b0 -
0/
0#
1%
1)
1(
1,
#760000
0%
0)
#765000
b1 4
b0 1
b1 -
1%
1)
#770000
0%
0)
#775000
b10 -
b1 1
b11000010 2
b11000010 !
1%
1)
0(
0,
#780000
0%
0)
#785000
b10 1
b11000000 2
b11000000 !
b11 -
1/
1#
1%
1)
#790000
0%
0)
#795000
b100 -
0/
0#
b11 1
b11000100 2
b11000100 !
1%
1)
#800000
0%
0)
#805000
b100 1
b11000100 2
b101 -
1/
1#
1%
1)
#810000
0%
0)
#815000
b110 -
0/
0#
b101 1
b11010100 2
b11010100 !
1%
1)
#820000
0%
0)
#825000
b110 1
b11010100 2
b111 -
1/
1#
1%
1)
#830000
0%
0)
#835000
b1000 -
b111 1
b11010100 2
1%
1)
#840000
0%
0)
#845000
b1000 1
b11010100 2
10
1$
b0 .
b1001 -
x/
x#
1%
1)
#850000
0%
0)
#855000
00
0$
13
1"
b0 4
b1001 1
1%
1)
#860000
0%
0)
#865000
03
0"
1%
1)
#870000
0%
0)
#875000
1%
1)
#880000
0%
0)
#885000
1%
1)
#890000
0%
0)
#895000
1%
1)
#900000
0%
0)
#905000
1%
1)
#910000
0%
0)
#915000
1%
1)
#920000
0%
0)
#925000
1%
1)
#930000
0%
0)
#935000
1%
1)
#940000
0%
0)
#945000
1%
1)
#950000
0%
0)
#955000
1%
1)
#960000
0%
0)
#965000
1%
1)
b100 &
b11100101 *
#970000
0%
0)
#975000
1%
1)
#980000
0%
0)
#985000
b1 .
b0 -
0/
0#
1%
1)
1(
1,
#990000
0%
0)
#995000
b1 -
1/
1#
b1 4
b0 1
1%
1)
#1000000
0%
0)
#1005000
b1 1
b11010101 2
b11010101 !
b10 -
0/
0#
1%
1)
0(
0,
#1010000
0%
0)
#1015000
b11 -
1/
1#
b10 1
b11010101 2
1%
1)
#1020000
0%
0)
#1025000
b11 1
b11010101 2
b100 -
0/
0#
1%
1)
#1030000
0%
0)
#1035000
b101 -
b100 1
b11010101 2
1%
1)
#1040000
0%
0)
#1045000
b101 1
b11000101 2
b11000101 !
b110 -
1/
1#
1%
1)
#1050000
0%
0)
#1055000
b111 -
b110 1
b11100101 2
b11100101 !
1%
1)
#1060000
0%
0)
#1065000
b111 1
b11100101 2
b1000 -
1%
1)
#1070000
0%
0)
#1075000
10
1$
b0 .
b1001 -
x/
x#
b1000 1
b11100101 2
1%
1)
#1080000
0%
0)
#1085000
13
1"
b0 4
b1001 1
00
0$
1%
1)
#1090000
0%
0)
#1095000
03
0"
1%
1)
#1100000
0%
0)
#1105000
1%
1)
#1110000
0%
0)
#1115000
1%
1)
#1120000
0%
0)
#1125000
1%
1)
#1130000
0%
0)
#1135000
1%
1)
#1140000
0%
0)
#1145000
1%
1)
#1150000
0%
0)
#1155000
1%
1)
#1160000
0%
0)
#1165000
1%
1)
#1170000
0%
0)
#1175000
1%
1)
#1180000
0%
0)
#1185000
1%
1)
#1190000
0%
0)
#1195000
1%
1)
b101 &
b11110110 *
#1200000
0%
0)
#1205000
1%
1)
#1210000
0%
0)
#1215000
b1 .
b0 -
0/
0#
1%
1)
1(
1,
#1220000
0%
0)
#1225000
b1 4
b0 1
b1 -
1%
1)
#1230000
0%
0)
#1235000
b10 -
1/
1#
b1 1
b11100100 2
b11100100 !
1%
1)
0(
0,
#1240000
0%
0)
#1245000
b10 1
b11100110 2
b11100110 !
b11 -
1%
1)
#1250000
0%
0)
#1255000
b100 -
0/
0#
b11 1
b11100110 2
1%
1)
#1260000
0%
0)
#1265000
b100 1
b11100110 2
b101 -
1/
1#
1%
1)
#1270000
0%
0)
#1275000
b110 -
b101 1
b11110110 2
b11110110 !
1%
1)
#1280000
0%
0)
#1285000
b110 1
b11110110 2
b111 -
1%
1)
#1290000
0%
0)
#1295000
b1000 -
b111 1
b11110110 2
1%
1)
#1300000
0%
0)
#1305000
b1000 1
b11110110 2
10
1$
b0 .
b1001 -
x/
x#
1%
1)
#1310000
0%
0)
#1315000
00
0$
13
1"
b0 4
b1001 1
1%
1)
#1320000
0%
0)
#1325000
03
0"
1%
1)
#1330000
0%
0)
#1335000
1%
1)
#1340000
0%
0)
#1345000
1%
1)
#1350000
0%
0)
#1355000
1%
1)
#1360000
0%
0)
#1365000
1%
1)
#1370000
0%
0)
#1375000
1%
1)
#1380000
0%
0)
#1385000
1%
1)
#1390000
0%
0)
#1395000
1%
1)
#1400000
0%
0)
#1405000
1%
1)
#1410000
0%
0)
#1415000
1%
1)
#1420000
0%
0)
#1425000
1%
1)
b110 &
b111 *
#1430000
0%
0)
#1435000
1%
1)
#1440000
0%
0)
#1445000
b1 .
b0 -
0/
0#
1%
1)
1(
1,
#1450000
0%
0)
#1455000
b1 -
1/
1#
b1 4
b0 1
1%
1)
#1460000
0%
0)
#1465000
b1 1
b11110111 2
b11110111 !
b10 -
1%
1)
0(
0,
#1470000
0%
0)
#1475000
b11 -
b10 1
b11110111 2
1%
1)
#1480000
0%
0)
#1485000
b11 1
b11110111 2
b100 -
0/
0#
1%
1)
#1490000
0%
0)
#1495000
b101 -
b100 1
b11110111 2
1%
1)
#1500000
0%
0)
#1505000
b101 1
b11100111 2
b11100111 !
b110 -
1%
1)
#1510000
0%
0)
#1515000
b111 -
b110 1
b11000111 2
b11000111 !
1%
1)
#1520000
0%
0)
#1525000
b111 1
b10000111 2
b10000111 !
b1000 -
1%
1)
#1530000
0%
0)
#1535000
10
1$
b0 .
b1001 -
x/
x#
b1000 1
b111 2
b111 !
1%
1)
#1540000
0%
0)
#1545000
13
1"
b0 4
b1001 1
00
0$
1%
1)
#1550000
0%
0)
#1555000
03
0"
1%
1)
#1560000
0%
0)
#1565000
1%
1)
#1570000
0%
0)
#1575000
1%
1)
#1580000
0%
0)
#1585000
1%
1)
#1590000
0%
0)
#1595000
1%
1)
#1600000
0%
0)
#1605000
1%
1)
#1610000
0%
0)
#1615000
1%
1)
#1620000
0%
0)
#1625000
1%
1)
#1630000
0%
0)
#1635000
1%
1)
#1640000
0%
0)
#1645000
1%
1)
#1650000
0%
0)
#1655000
1%
1)
b111 &
b11000 *
#1660000
0%
0)
#1665000
1%
1)
#1670000
0%
0)
#1675000
b1 .
b0 -
0/
0#
1%
1)
1(
1,
#1680000
0%
0)
#1685000
b1 4
b0 1
b1 -
1%
1)
#1690000
0%
0)
#1695000
b10 -
b1 1
b110 2
b110 !
1%
1)
0(
0,
#1700000
0%
0)
#1705000
b10 1
b100 2
b100 !
b11 -
1%
1)
#1710000
0%
0)
#1715000
b100 -
1/
1#
b11 1
b0 2
b0 !
1%
1)
#1720000
0%
0)
#1725000
b100 1
b1000 2
b1000 !
b101 -
1%
1)
#1730000
0%
0)
#1735000
b110 -
0/
0#
b101 1
b11000 2
b11000 !
1%
1)
#1740000
0%
0)
#1745000
b110 1
b11000 2
b111 -
1%
1)
#1750000
0%
0)
#1755000
b1000 -
b111 1
b11000 2
1%
1)
#1760000
0%
0)
#1765000
b1000 1
b11000 2
10
1$
b0 .
b1001 -
x/
x#
1%
1)
#1770000
0%
0)
#1775000
00
0$
13
1"
b0 4
b1001 1
1%
1)
#1780000
0%
0)
#1785000
03
0"
1%
1)
#1790000
0%
0)
#1795000
1%
1)
#1800000
0%
0)
#1805000
1%
1)
#1810000
0%
0)
#1815000
1%
1)
#1820000
0%
0)
#1825000
1%
1)
#1830000
0%
0)
#1835000
1%
1)
#1840000
0%
0)
#1845000
1%
1)
#1850000
0%
0)
#1855000
1%
1)
#1860000
0%
0)
#1865000
1%
1)
#1870000
0%
0)
#1875000
1%
1)
#1880000
0%
0)
#1885000
1%
1)
b1000 &
b101001 *
#1890000
0%
0)
#1895000
1%
1)
#1900000
0%
0)
#1905000
b1 .
b0 -
0/
0#
1%
1)
1(
1,
#1910000
0%
0)
#1915000
b1 -
1/
1#
b1 4
b0 1
1%
1)
#1920000
0%
0)
#1925000
b1 1
b11001 2
b11001 !
b10 -
0/
0#
1%
1)
0(
0,
#1930000
0%
0)
#1935000
b11 -
b10 1
b11001 2
1%
1)
#1940000
0%
0)
#1945000
b11 1
b11001 2
b100 -
1/
1#
1%
1)
#1950000
0%
0)
#1955000
b101 -
0/
0#
b100 1
b11001 2
1%
1)
#1960000
0%
0)
#1965000
b101 1
b1001 2
b1001 !
b110 -
1/
1#
1%
1)
#1970000
0%
0)
#1975000
b111 -
0/
0#
b110 1
b101001 2
b101001 !
1%
1)
#1980000
0%
0)
#1985000
b111 1
b101001 2
b1000 -
1%
1)
#1990000
0%
0)
#1995000
10
1$
b0 .
b1001 -
x/
x#
b1000 1
b101001 2
1%
1)
#2000000
0%
0)
#2005000
13
1"
b0 4
b1001 1
00
0$
1%
1)
#2010000
0%
0)
#2015000
03
0"
1%
1)
#2020000
0%
0)
#2025000
1%
1)
#2030000
0%
0)
#2035000
1%
1)
#2040000
0%
0)
#2045000
1%
1)
#2050000
0%
0)
#2055000
1%
1)
#2060000
0%
0)
#2065000
1%
1)
#2070000
0%
0)
#2075000
1%
1)
#2080000
0%
0)
#2085000
1%
1)
#2090000
0%
0)
#2095000
1%
1)
#2100000
0%
0)
#2105000
1%
1)
#2110000
0%
0)
#2115000
1%
1)
b1001 &
b111010 *
#2120000
0%
0)
#2125000
1%
1)
#2130000
0%
0)
#2135000
b1 .
b0 -
0/
0#
1%
1)
1(
1,
#2140000
0%
0)
#2145000
b1 4
b0 1
b1 -
1%
1)
#2150000
0%
0)
#2155000
b10 -
1/
1#
b1 1
b101000 2
b101000 !
1%
1)
0(
0,
#2160000
0%
0)
#2165000
b10 1
b101010 2
b101010 !
b11 -
0/
0#
1%
1)
#2170000
0%
0)
#2175000
b100 -
1/
1#
b11 1
b101010 2
1%
1)
#2180000
0%
0)
#2185000
b100 1
b101010 2
b101 -
1%
1)
#2190000
0%
0)
#2195000
b110 -
b101 1
b111010 2
b111010 !
1%
1)
#2200000
0%
0)
#2205000
b110 1
b111010 2
b111 -
0/
0#
1%
1)
#2210000
0%
0)
#2215000
b1000 -
b111 1
b111010 2
1%
1)
#2220000
0%
0)
#2225000
b1000 1
b111010 2
10
1$
b0 .
b1001 -
x/
x#
1%
1)
#2230000
0%
0)
#2235000
00
0$
13
1"
b0 4
b1001 1
1%
1)
#2240000
0%
0)
#2245000
03
0"
1%
1)
#2250000
0%
0)
#2255000
1%
1)
#2260000
0%
0)
#2265000
1%
1)
#2270000
0%
0)
#2275000
1%
1)
#2280000
0%
0)
#2285000
1%
1)
#2290000
0%
0)
#2295000
1%
1)
#2300000
0%
0)
#2305000
1%
1)
#2310000
0%
0)
#2315000
1%
1)
#2320000
0%
0)
#2325000
1%
1)
#2330000
0%
0)
#2335000
1%
1)
#2340000
0%
0)
#2345000
1%
1)
b1010 &
bx *
